fractalic.py
core/__init__.py
core/_rep_build.py
core/config.py
core/errors.py
core/git.py
core/linter.py
core/paths.py
core/simple_token_tracker.py
core/token_tracker.py
core/utils.py
core/ast_md/__init___1.py
core/ast_md/ast.py
core/ast_md/node.py
core/ast_md/parser.py
core/llm/__init__.py
core/llm/llm_client.py
core/llm/providers/__init__.py
core/llm/providers/openai_client.py
core/llm/providers/rich_formatter.py
core/operations/__init__.py
core/operations/call_tree.py
core/operations/goto_op.py
core/operations/import_op.py
core/operations/llm_op.py
core/operations/return_op.py
core/operations/runner.py
core/operations/shell_op.py
core/plugins/cli_introspect.py
core/plugins/mcp_client.py
core/plugins/tool_registry.py
core/render/__init__.py
core/render/render_ast.py
core/ui_server/server.py
fractalic-0.1.6.dist-info/licenses/LICENSE.txt
fractalic-0.1.6.dist-info/METADATA
fractalic-0.1.6.dist-info/WHEEL
fractalic-0.1.6.dist-info/entry_points.txt
fractalic-0.1.6.dist-info/top_level.txt
fractalic-0.1.6.dist-info/RECORD
