Metadata-Version: 2.4
Name: fractalic
Version: 0.1.6
Summary: The Agentic Development Environment - Turn simple documents into powerful, AI-native applications
Author-email: Fractalic AI <hello@fractalic.ai>
Maintainer-email: Fractalic AI <hello@fractalic.ai>
License: MIT
Project-URL: Homepage, https://fractalic.ai
Project-URL: Documentation, https://fractalic.ai/docs
Project-URL: Repository, https://github.com/fractalic-ai/fractalic
Project-URL: Issues, https://github.com/fractalic-ai/fractalic/issues
Project-URL: Discord, https://discord.gg/DHbnvxAT
Keywords: ai,agents,automation,markdown,llm,agentic,development,mcp,model-context-protocol,workflow,orchestration
Classifier: Development Status :: 4 - Beta
Classifier: Intended Audience :: Developers
Classifier: Operating System :: OS Independent
Classifier: Programming Language :: Python :: 3
Classifier: Programming Language :: Python :: 3.11
Classifier: Programming Language :: Python :: 3.12
Classifier: Topic :: Software Development :: Libraries :: Python Modules
Classifier: Topic :: Scientific/Engineering :: Artificial Intelligence
Classifier: Topic :: Text Processing :: Markup
Classifier: Topic :: System :: Shells
Requires-Python: >=3.11
License-File: LICENSE.txt
Requires-Dist: anthropic>=0.8.0
Requires-Dist: aiohttp>=3.9.0
Requires-Dist: aiohttp-cors
Requires-Dist: python-dotenv>=1.0.0
Requires-Dist: groq
Requires-Dist: openai
Requires-Dist: litellm>=1.70.0
Requires-Dist: requests
Requires-Dist: replicate
Requires-Dist: uvicorn
Requires-Dist: fastapi==0.115.6
Requires-Dist: gitpython==3.1.41
Requires-Dist: jsonschema==4.23.0
Requires-Dist: Pillow>=10.0.0
Requires-Dist: PyYAML==6.0.2
Requires-Dist: rich==13.9.4
Requires-Dist: toml==0.10.2
Requires-Dist: mcp==1.11.0
Requires-Dist: fastmcp>=2.10.0
Requires-Dist: tiktoken
Requires-Dist: httpx>=0.27.0
Requires-Dist: pydantic>=2.7.0
Provides-Extra: dev
Requires-Dist: pytest; extra == "dev"
Requires-Dist: pytest-asyncio; extra == "dev"
Requires-Dist: black; extra == "dev"
Requires-Dist: flake8; extra == "dev"
Requires-Dist: mypy; extra == "dev"
Dynamic: license-file
